{
 "2020-04-27 17:10":{
  "m":4.84,
  "nc":1,
  "ng":1,
  "tr":3,
  "tt":0
 },
 "2020-04-27 17:40":{
  "m":4.9,
  "nc":1,
  "ng":1,
  "tr":3,
  "tt":0
 },
 "2020-04-27 18:10":{
  "m":4.61,
  "nc":1,
  "ng":1,
  "tr":3,
  "tt":0
 },
 "2020-04-27 18:40":{
  "m":5.18,
  "nc":1,
  "ng":1,
  "tr":3,
  "tt":0
 },
 "2020-04-27 19:30":{
  "m":4.49,
  "nc":0,
  "ng":1,
  "tr":3,
  "tt":0
 },
 "2020-04-27 19:40":{
  "m":4.44,
  "nc":0,
  "ng":1,
  "tr":3,
  "tt":0
 },
 "2020-04-27 20:10":{
  "m":4.38,
  "nc":0,
  "ng":1,
  "tr":3,
  "tt":0
 },
 "2020-04-27 20:40":{
  "m":4.8,
  "nc":1,
  "ng":1,
  "tr":3,
  "tt":0
 },
 "2020-04-27 21:10":{
  "m":4.74,
  "nc":1,
  "ng":1,
  "tr":3,
  "tt":0
 },
 "2020-04-27 21:40":{
  "m":5.08,
  "nc":1,
  "ng":1,
  "tr":3,
  "tt":0
 },
 "2020-04-27 22:42":{
  "m":4.56,
  "nc":2,
  "ng":1,
  "tr":3,
  "tt":0
 },
 "2020-04-27 23:12":{
  "m":4.75,
  "nc":1,
  "ng":1,
  "tr":3,
  "tt":0
 }
}